odoo/addons/fieldservice_purchase/README.rst
odoo/addons/fieldservice_purchase/__init__.py
odoo/addons/fieldservice_purchase/__manifest__.py
odoo/addons/fieldservice_purchase/i18n/de.po
odoo/addons/fieldservice_purchase/i18n/es_CL.po
odoo/addons/fieldservice_purchase/i18n/fieldservice_purchase.pot
odoo/addons/fieldservice_purchase/i18n/pt_BR.po
odoo/addons/fieldservice_purchase/models/__init__.py
odoo/addons/fieldservice_purchase/models/fsm_person.py
odoo/addons/fieldservice_purchase/readme/CONTRIBUTORS.rst
odoo/addons/fieldservice_purchase/readme/CREDITS.rst
odoo/addons/fieldservice_purchase/readme/DESCRIPTION.rst
odoo/addons/fieldservice_purchase/readme/ROADMAP.rst
odoo/addons/fieldservice_purchase/readme/USAGE.rst
odoo/addons/fieldservice_purchase/security/ir.model.access.csv
odoo/addons/fieldservice_purchase/static/description/icon.png
odoo/addons/fieldservice_purchase/static/description/index.html
odoo/addons/fieldservice_purchase/views/fsm_person.xml
odoo12_addon_fieldservice_purchase-12.0.1.1.0.dist-info/METADATA
odoo12_addon_fieldservice_purchase-12.0.1.1.0.dist-info/WHEEL
odoo12_addon_fieldservice_purchase-12.0.1.1.0.dist-info/top_level.txt
odoo12_addon_fieldservice_purchase-12.0.1.1.0.dist-info/RECORD
